{
  "docs": {
    "About Milagro": 
      [
        "milagro-intro", 
        "milagro-crypto",
        "milagro-protocols",
        "milagro-design"
      ],
    "AMCL Library": 
      [
        "amcl-overview",                    
        "amcl-c-api",
        "amcl-javascript-api"
      ],
    "Decentralized Trust Authority": 
      [
        "d-ta-overview",
        "dta-details/quickstart",
        "dta-details/api",
        "dta-details/configuration",
		"dta-details/identity-documents",
		"dta-details/encrypted-envelope",
		"dta-details/ipfs",
		"dta-details/plugins-overview",
		"dta-details/authentication"
    ],  
    "ZKP-MFA Clients/Servers": [
      "zkp-mfa-overview",
      "zkp-mfa-api"
    ],
    "Project Info": [
      "contributor-guide",
	  "downloads",
      "../help",
      "../blog"
    ]
  }
}
